fhs.py
fhs_paths-1.2.dist-info/METADATA
fhs_paths-1.2.dist-info/WHEEL
fhs_paths-1.2.dist-info/copyright
fhs_paths-1.2.dist-info/top_level.txt
fhs_paths-1.2.dist-info/RECORD
